odoo/addons/account_due_list_edit_inline/README.rst
odoo/addons/account_due_list_edit_inline/__init__.py
odoo/addons/account_due_list_edit_inline/__manifest__.py
odoo/addons/account_due_list_edit_inline/i18n/account_due_list_edit_inline.pot
odoo/addons/account_due_list_edit_inline/i18n/it.po
odoo/addons/account_due_list_edit_inline/readme/CONFIGURE.rst
odoo/addons/account_due_list_edit_inline/readme/CONTRIBUTORS.rst
odoo/addons/account_due_list_edit_inline/readme/DESCRIPTION.rst
odoo/addons/account_due_list_edit_inline/readme/USAGE.rst
odoo/addons/account_due_list_edit_inline/static/description/icon.png
odoo/addons/account_due_list_edit_inline/static/description/index.html
odoo/addons/account_due_list_edit_inline/views/payment_view.xml
odoo14_addon_account_due_list_edit_inline-14.0.1.0.1.dev4.dist-info/METADATA
odoo14_addon_account_due_list_edit_inline-14.0.1.0.1.dev4.dist-info/WHEEL
odoo14_addon_account_due_list_edit_inline-14.0.1.0.1.dev4.dist-info/top_level.txt
odoo14_addon_account_due_list_edit_inline-14.0.1.0.1.dev4.dist-info/RECORD
